{
	"cmake" : 
	{
		"generator" : 
		{
			"multiConfig" : false,
			"name" : "Ninja"
		},
		"paths" : 
		{
			"cmake" : "/home/notroot/\u0417\u0430\u0433\u0440\u0443\u0437\u043a\u0438/clion-2022.1.1/bin/cmake/linux/bin/cmake",
			"cpack" : "/home/notroot/\u0417\u0430\u0433\u0440\u0443\u0437\u043a\u0438/clion-2022.1.1/bin/cmake/linux/bin/cpack",
			"ctest" : "/home/notroot/\u0417\u0430\u0433\u0440\u0443\u0437\u043a\u0438/clion-2022.1.1/bin/cmake/linux/bin/ctest",
			"root" : "/home/notroot/\u0417\u0430\u0433\u0440\u0443\u0437\u043a\u0438/clion-2022.1.1/bin/cmake/linux/share/cmake-3.22"
		},
		"version" : 
		{
			"isDirty" : false,
			"major" : 3,
			"minor" : 22,
			"patch" : 3,
			"string" : "3.22.3",
			"suffix" : ""
		}
	},
	"objects" : 
	[
		{
			"jsonFile" : "codemodel-v2-5ae8e35075e4cfa1d0b4.json",
			"kind" : "codemodel",
			"version" : 
			{
				"major" : 2,
				"minor" : 3
			}
		},
		{
			"jsonFile" : "cache-v2-c3c8f3ca6fa79153b7e7.json",
			"kind" : "cache",
			"version" : 
			{
				"major" : 2,
				"minor" : 0
			}
		},
		{
			"jsonFile" : "cmakeFiles-v1-788e17c9eab91b0a9165.json",
			"kind" : "cmakeFiles",
			"version" : 
			{
				"major" : 1,
				"minor" : 0
			}
		},
		{
			"jsonFile" : "toolchains-v1-a0821f36b07187ce1798.json",
			"kind" : "toolchains",
			"version" : 
			{
				"major" : 1,
				"minor" : 0
			}
		}
	],
	"reply" : 
	{
		"cache-v2" : 
		{
			"jsonFile" : "cache-v2-c3c8f3ca6fa79153b7e7.json",
			"kind" : "cache",
			"version" : 
			{
				"major" : 2,
				"minor" : 0
			}
		},
		"cmakeFiles-v1" : 
		{
			"jsonFile" : "cmakeFiles-v1-788e17c9eab91b0a9165.json",
			"kind" : "cmakeFiles",
			"version" : 
			{
				"major" : 1,
				"minor" : 0
			}
		},
		"codemodel-v2" : 
		{
			"jsonFile" : "codemodel-v2-5ae8e35075e4cfa1d0b4.json",
			"kind" : "codemodel",
			"version" : 
			{
				"major" : 2,
				"minor" : 3
			}
		},
		"toolchains-v1" : 
		{
			"jsonFile" : "toolchains-v1-a0821f36b07187ce1798.json",
			"kind" : "toolchains",
			"version" : 
			{
				"major" : 1,
				"minor" : 0
			}
		}
	}
}
